pyvisa/__init__.py
pyvisa/attributes.py
pyvisa/cmd_line_tools.py
pyvisa/constants.py
pyvisa/errors.py
pyvisa/events.py
pyvisa/highlevel.py
pyvisa/py.typed
pyvisa/rname.py
pyvisa/shell.py
pyvisa/typing.py
pyvisa/util.py
pyvisa/version.py
pyvisa/ctwrapper/__init__.py
pyvisa/ctwrapper/cthelper.py
pyvisa/ctwrapper/functions.py
pyvisa/ctwrapper/highlevel.py
pyvisa/ctwrapper/types.py
pyvisa/resources/__init__.py
pyvisa/resources/firewire.py
pyvisa/resources/gpib.py
pyvisa/resources/messagebased.py
pyvisa/resources/pxi.py
pyvisa/resources/registerbased.py
pyvisa/resources/resource.py
pyvisa/resources/serial.py
pyvisa/resources/tcpip.py
pyvisa/resources/usb.py
pyvisa/resources/vxi.py
pyvisa/testsuite/__init__.py
pyvisa/testsuite/test_attributes.py
pyvisa/testsuite/test_cmd_line_tools.py
pyvisa/testsuite/test_constants.py
pyvisa/testsuite/test_env_var_handling.py
pyvisa/testsuite/test_errors.py
pyvisa/testsuite/test_event.py
pyvisa/testsuite/test_highlevel.py
pyvisa/testsuite/test_logging_utilities.py
pyvisa/testsuite/test_rname.py
pyvisa/testsuite/test_util.py
pyvisa/testsuite/fake-extensions/pyvisa_test.py
pyvisa/testsuite/fake-extensions/pyvisa_test_open.py
pyvisa/testsuite/keysight_assisted_tests/__init__.py
pyvisa/testsuite/keysight_assisted_tests/messagebased_resource_utils.py
pyvisa/testsuite/keysight_assisted_tests/resource_utils.py
pyvisa/testsuite/keysight_assisted_tests/test_resource_manager.py
pyvisa/testsuite/keysight_assisted_tests/test_rname_filter2.py
pyvisa/testsuite/keysight_assisted_tests/test_shell.py
pyvisa/testsuite/keysight_assisted_tests/test_tcpip_resources.py
pyvisa/testsuite/keysight_assisted_tests/test_util.py
pyvisa/thirdparty/__init__.py
pyvisa/thirdparty/prettytable.py
pyvisa-1.16.0.dist-info/licenses/AUTHORS
pyvisa-1.16.0.dist-info/licenses/LICENSE
pyvisa-1.16.0.dist-info/METADATA
pyvisa-1.16.0.dist-info/WHEEL
pyvisa-1.16.0.dist-info/entry_points.txt
pyvisa-1.16.0.dist-info/top_level.txt
pyvisa-1.16.0.dist-info/RECORD
