Metadata-Version: 2.4
Name: PyVISA
Version: 1.16.0
Summary: Python VISA bindings for GPIB, RS232, TCPIP and USB instruments
Author: Gregor Thalhammer
Author-email: Torsten Bronger <bronger@physik.rwth-aachen.de>, "Hernan E. Grecco" <hernan.grecco@gmail.com>
Maintainer-email: "Matthieu C. Dartiailh" <m.dartiailh@gmail.com>
License: The MIT License
Project-URL: homepage, https://github.com/pyvisa/pyvisa
Project-URL: documentation, https://pyvisa.readthedocs.io/en/latest/
Project-URL: repository, https://github.com/pyvisa/pyvisa
Project-URL: changelog, https://github.com/pyvisa/pyvisa/blob/main/CHANGES
Keywords: VISA,GPIB,USB,serial,RS232,measurement,acquisition
Classifier: Development Status :: 5 - Production/Stable
Classifier: Intended Audience :: Developers
Classifier: Intended Audience :: Science/Research
Classifier: License :: OSI Approved :: MIT License
Classifier: Operating System :: Microsoft :: Windows
Classifier: Operating System :: POSIX :: Linux
Classifier: Operating System :: MacOS :: MacOS X
Classifier: Programming Language :: Python
Classifier: Topic :: Scientific/Engineering :: Interface Engine/Protocol Translator
Classifier: Topic :: Software Development :: Libraries :: Python Modules
Classifier: Programming Language :: Python :: 3
Classifier: Programming Language :: Python :: 3.10
Classifier: Programming Language :: Python :: 3.11
Classifier: Programming Language :: Python :: 3.12
Classifier: Programming Language :: Python :: 3.13
Classifier: Programming Language :: Python :: 3.14
Requires-Python: >=3.10
License-File: LICENSE
License-File: AUTHORS
Requires-Dist: typing_extensions>=4.0.0
Dynamic: license-file
